pidgin/__init__.py
pidgin/__main__.py
pidgin/py.typed
pidgin/analysis/__init__.py
pidgin/analysis/convergence.py
pidgin/analysis/notebook_cells.py
pidgin/analysis/notebook_generator.py
pidgin/analysis/cells/__init__.py
pidgin/analysis/cells/base.py
pidgin/analysis/cells/convergence.py
pidgin/analysis/cells/setup.py
pidgin/analysis/cells/statistics.py
pidgin/analysis/cells/visualization.py
pidgin/analysis/cells/vocabulary.py
pidgin/cli/__init__.py
pidgin/cli/branch.py
pidgin/cli/config.py
pidgin/cli/config_builder.py
pidgin/cli/constants.py
pidgin/cli/daemon_launcher.py
pidgin/cli/display_manager.py
pidgin/cli/error_handler.py
pidgin/cli/helpers.py
pidgin/cli/model_selector.py
pidgin/cli/models.py
pidgin/cli/monitor.py
pidgin/cli/name_generator.py
pidgin/cli/notify.py
pidgin/cli/ollama_setup.py
pidgin/cli/run.py
pidgin/cli/spec_loader.py
pidgin/cli/stop.py
pidgin/cli/branch_handlers/__init__.py
pidgin/cli/branch_handlers/config_builder.py
pidgin/cli/branch_handlers/executor.py
pidgin/cli/branch_handlers/models.py
pidgin/cli/branch_handlers/source_finder.py
pidgin/cli/branch_handlers/spec_writer.py
pidgin/cli/run_handlers/__init__.py
pidgin/cli/run_handlers/command_handler.py
pidgin/cli/run_handlers/execution.py
pidgin/cli/run_handlers/models.py
pidgin/cli/run_handlers/setup.py
pidgin/cli/run_handlers/spec_handler.py
pidgin/config/__init__.py
pidgin/config/config.py
pidgin/config/defaults.py
pidgin/config/model_loader.py
pidgin/config/model_types.py
pidgin/config/models.py
pidgin/config/prompts.py
pidgin/config/provider_capabilities.py
pidgin/config/resolution.py
pidgin/config/schema.py
pidgin/config/system_prompts.py
pidgin/core/__init__.py
pidgin/core/app_context.py
pidgin/core/conductor.py
pidgin/core/constants.py
pidgin/core/conversation_lifecycle.py
pidgin/core/conversation_setup.py
pidgin/core/conversation_state.py
pidgin/core/event_bus.py
pidgin/core/events.py
pidgin/core/exceptions.py
pidgin/core/interrupt_handler.py
pidgin/core/message_handler.py
pidgin_ai-1.0.0.dist-info/METADATA
pidgin_ai-1.0.0.dist-info/WHEEL
pidgin_ai-1.0.0.dist-info/entry_points.txt
pidgin_ai-1.0.0.dist-info/licenses/LICENSE
pidgin_ai-1.0.0.dist-info/RECORD
