Metadata-Version: 2.4
Name: pidgin-ai
Version: 1.0.0
Summary: AI conversation research tool for studying emergent communication patterns
Project-URL: Homepage, https://github.com/tensegrity-ai/pidgin
Project-URL: Repository, https://github.com/tensegrity-ai/pidgin
Project-URL: Documentation, https://github.com/tensegrity-ai/pidgin#readme
Author-email: Your Name <your.email@example.com>
License: MIT
License-File: LICENSE
Keywords: ai,anthropic,communication,conversation,llm,openai,research
Classifier: Development Status :: 4 - Beta
Classifier: Intended Audience :: Developers
Classifier: Intended Audience :: Science/Research
Classifier: License :: OSI Approved :: MIT License
Classifier: Programming Language :: Python :: 3
Classifier: Programming Language :: Python :: 3.9
Classifier: Programming Language :: Python :: 3.10
Classifier: Programming Language :: Python :: 3.11
Classifier: Programming Language :: Python :: 3.12
Classifier: Topic :: Scientific/Engineering :: Artificial Intelligence
Classifier: Topic :: Software Development :: Libraries :: Python Modules
Requires-Python: <3.14,>=3.11
Requires-Dist: aiohttp>=3.9.0
Requires-Dist: anthropic<1.0.0,>=0.25.0
Requires-Dist: click>=8.0.0
Requires-Dist: duckdb>=1.1.3
Requires-Dist: google-generativeai>=0.8.0
Requires-Dist: openai>=1.0.0
Requires-Dist: pydantic>=2.0.0
Requires-Dist: python-dotenv>=1.0.0
Requires-Dist: pyyaml>=6.0.0
Requires-Dist: requests>=2.32.4
Requires-Dist: rich-click>=1.8.0
Requires-Dist: rich>=13.0.0
Requires-Dist: setproctitle>=1.3
Requires-Dist: urllib3>=2.5.0
